[
{ "name": "Ciudad de México Terminal Norte", "position": [19.342505677895627, -99.13878463558224], "state": "Distrito Federal", "phone": "800 800 0386", "address": "Calz Taxqueña 1320, Campestre Churubusco, 04200 Ciudad de México, CDMX" },
{ "name": "Ciudad de Mexico Terminal Norte", "position": [19.47980546032392, -99.13883530674671], "state": "Distrito Federal", "phone": "800 003 7635", "address": "Eje Central Lázaro Cárdenas 4907, Magdalena de las Salinas, 07760 Gustavo A. Madero, CDMX" },
{ "name": "Ciudad de Mexico Terminal Poniente", "position": [19.39672291904422, -99.19961366256912], "state": "Distrito Federal", "phone": "800 003 7635", "address": "Av. Río Tacubaya s/n, Col. Real del Monte, Central Camionera Poniente, 01130 Álvaro Obregón, CDMX" },
{ "name": "Ciudad de Mexico Rio Tiber", "position": [19.430603936683905, -99.16931357791118], "state": "Distrito Federal", "phone": "800 003 7635", "address": "C. Río Tiber 74, Cuauhtémoc, 06500 Ciudad de México, CDMX" },

{ "name": "Acapulco Centro", "position": [16.85657144108208, -99.90142083558224], "state": "Guerrero", "phone": "s/n", "address": "Av Cuauhtémoc 84, Equipamiento, Acapulco de Juárez, Gro." },
{ "name": "Acapulco Ejido", "position": [16.86247727407811, -99.90867390674671], "state": "Guerrero", "phone": "800 003 7635", "address": "Av. Ejido No. 47 Col. Palmar del Carabali, Aguas Blancas, Hogar Moderno, 39189 Acapulco de Juárez, Gro." },
{ "name": "Acapulco Papagayo", "position": [16.862212915309097, -99.8887651297515], "state": "Guerrero", "phone": "55 5089 9210", "address": "Av Cuauhtémoc 103, Equipamiento, 39300 Acapulco de Juárez, Gro." },
{ "name": "Acapulco Diamante", "position": [16.789786470605257, -99.8007650331262], "state": "Guerrero", "phone": "800 003 7635", "address": "Boulevard de las Naciones, 71, Granjas del Marqués, CP. 39890, Acapulco de Juárez, Gro." },
{ "name": "Arcelia", "position": [18.32299769010664, -100.28485225092432], "state": "Guerrero", "phone": "800 003 7635", "address": "Altamirano S/N Col. Héroes Surianos, 40500 Arcelia, Gro." },
{ "name": "Atoyac", "position": [17.20644630309478, -100.43766579325327], "state": "Guerrero", "phone": "800 003 7635", "address": "Av. Juan Nepomucenoas Alvarez 91, Centro, 40930 Atoyac de Álvarez, Gro." },
{ "name": "Chilpancingo", "position": [17.56217993083971, -99.51002889325328], "state": "Guerrero", "phone": "01 (747) 478 4250, 01 (747) 471 2580", "address": "Calle 21 de Marzo S/N, Benito Juárez, 39010 Chilpancingo de los Bravo, Gro." },
{ "name": "Ciudad Altamirano", "position": [18.358787284650333, -100.67366900859537], "state": "Guerrero", "phone": "800 003 7635", "address": "Rey Irepan Pte. 400, Col del Centro, 40660 Cd Altamirano, Gro." },
{ "name": "Coyuca", "position": [17.00827772565728, -100.08960609325328], "state": "Guerrero", "phone": "55 5484 1800", "address": "Zihuatanejo - Acapulco & Calle Constitución, Centro, 40970 Coyuca de Benítez, Gro." },
{ "name": "Iguala", "position": [18.33963729876116, -99.54127900859535], "state": "Guerrero", "phone": "800 003 7635", "address": "Calle De Salazar 1 Centro, GRO, México" },
{ "name": "Ixtapa Zihuatanejo", "position": [17.66225058873984, -101.60141883558222], "state": "Guerrero", "phone": "800 003 7635", "address": "Plaza los portales Local 4 And. Punta Carrizo. Col. Ixtapa, 40882 Ixtapa Zihuatanejo, Gro." },
{ "name": "Las cruces", "position": [16.88835417428105, -99.83666851593371], "state": "Guerrero", "phone": "800 003 7635", "address": "Blvd. Vicente Guerrero S/N, Las Cruces, 39770 Acapulco de Juárez, Gro." },
{ "name": "Petetlan", "position": [17.538231297018957, -101.2694245220888], "state": "Guerrero", "phone": "800 003 7635", "address": "Allende S/N Col. Centro, 40830 Petatlán, Gro." },
{ "name": "San Jeronimo", "position": [20.619875471506727, -103.28614080402697], "state": "Guerrero", "phone": "s/n", "address": "40960, Zihuatanejo - Acapulco 5763, Industrial, San Jerónimo de Juárez, Gro." },
{ "name": "Taxco", "position": [18.555565283286217, -99.60226459325328], "state": "Guerrero", "phone": "55 5484 1800", "address": "De Los Plateros 386, Centro, 40200 Taxco, Gro." },
{ "name": "Tecpan", "position": [17.22228434081367, -100.62998796256912], "state": "Guerrero", "phone": "55 5484 1800", "address": "Av. San Bartolo 6, Centro, 40900 Técpan de Galeana, Gro." },
{ "name": "Teloloapan", "position": [18.366331255417634, -99.86444528770737], "state": "Guerrero", "phone": "800 003 7635", "address": "Calz. Club de Leones S/N, Col. Emiliano Zapata, 40400 Teloloapan, Gro." },
{ "name": "Zihuatanejo", "position": [17.649496450141093, -101.54393209325328], "state": "Guerrero", "phone": "55 5484 1800", "address": "Av. Paseo de Zihuatanejo Ote. 57, Zona Industrial, 40880 Zihuatanejo, Gro." },

{ "name": "Lázaro Cárdenas", "position": [17.956756546731103, -102.19492317791119], "state": "Michoacán", "phone": "800 003 7635", "address": "Avenida Francisco I. Madero #65, colonia Centro, Lazaro Cardenas Michoacán" },

{ "name": "Estado de México Tepotzotlán", "position": [19.706175854213896, -99.20490463558224], "state": "México", "phone": "800 003 7635", "address": "Carretera México - Queretaro Km. 164, Col. Cedros, 54605 Tepotzotlán, Méx." },
{ "name": "Estado de Mexico Cuatla", "position": [18.812172325014483, -98.95317080674671], "state": "México", "phone": "800 003 7635", "address": "2 de Mayo entre De Vázquez y Mongoy No. 10 Col. Centro, 62740 Cuautla, Mor." },

{ "name": "Caseta de Alpuyeca", "position": [18.724055724589373, -99.25921536441774], "state": "Morelos", "phone": "(01) 55 5484 1800", "address": "Antigua Caseta Alpuyeca, Carretera México - Acapulco Km 115, 62797 Alpuyeca, Mor." },
{ "name": "Cuernavaca", "position": [19.34241853258092, -99.13859546714735], "state": "Morelos", "phone": "(01) 777 312 5716, 777 312", "address": "Av. Jose Maria Morelos Sur No. 329, Centro, 72000 Cuernavaca, MOR, México" },
{ "name": "Puente de Ixtla", "position": [18.617319323731813, -99.32404718436854], "state": "Morelos", "phone": "800 003 7635", "address": "Av Hidalgo 105, Centro, 62660 Puente de Ixtla, Mor." }
]